xxxparser/__init__.py
xxxparser/onpornfun.py
xxxparser/pornhub.py
xxxparser/sexstudentki.py
xxxparser/sunporno.py
xxxparser/tube8.py
xxxparser/tumblr.py
xxxparser/updatetube.py
xxxparser/video24.py
xxxparser/xvideos.py
xxxparser/youporn.py
xxxparser-0.1.2.dist-info/METADATA
xxxparser-0.1.2.dist-info/WHEEL
xxxparser-0.1.2.dist-info/top_level.txt
xxxparser-0.1.2.dist-info/RECORD
