Metadata-Version: 2.4
Name: xxxparser
Version: 0.1.2
Summary: A simple Python scripts for parsing some Adults websites
Author-email: pi11 <webii@pm.me>
Project-URL: Homepage, https://github.com/pi11/xxxparser
Classifier: Programming Language :: Python :: 3
Classifier: Operating System :: OS Independent
Requires-Python: >=3.6
Requires-Dist: requests
Requires-Dist: pyquery
